arc/__init__.py
arc/__main__.py
arc/client.py
arc/errors.py
arc/events.py
arc/extension.py
arc/locale.py
arc/plugin.py
arc/py.typed
arc/abc/__init__.py
arc/abc/client.py
arc/abc/command.py
arc/abc/concurrency_limiting.py
arc/abc/error_handler.py
arc/abc/hookable.py
arc/abc/limiter.py
arc/abc/option.py
arc/abc/plugin.py
arc/command/__init__.py
arc/command/message.py
arc/command/slash.py
arc/command/user.py
arc/command/option/__init__.py
arc/command/option/attachment.py
arc/command/option/bool.py
arc/command/option/channel.py
arc/command/option/float.py
arc/command/option/int.py
arc/command/option/mentionable.py
arc/command/option/role.py
arc/command/option/str.py
arc/command/option/user.py
arc/command/option/custom/__init__.py
arc/command/option/custom/color.py
arc/command/option/custom/emoji.py
arc/command/option/custom/member.py
arc/context/__init__.py
arc/context/autocomplete.py
arc/context/base.py
arc/ext/__init__.py
arc/internal/__init__.py
arc/internal/about.py
arc/internal/deprecation.py
arc/internal/options.py
arc/internal/sigparse.py
arc/internal/sync.py
arc/internal/types.py
arc/internal/version.py
arc/utils/__init__.py
arc/utils/concurrency_limiter.py
arc/utils/loops.py
arc/utils/ratelimiter.py
arc/utils/hooks/__init__.py
arc/utils/hooks/basic.py
arc/utils/hooks/limiters.py
hikari_arc-2.1.1.dist-info/METADATA
hikari_arc-2.1.1.dist-info/WHEEL
hikari_arc-2.1.1.dist-info/licenses/LICENSE
hikari_arc-2.1.1.dist-info/RECORD
