Metadata-Version: 2.4
Name: hikari-arc
Version: 2.1.1
Summary: A command handler for hikari with a focus on type-safety and correctness.
Project-URL: Homepage, https://arc.hypergonial.com
Project-URL: Documentation, https://arc.hypergonial.com
Project-URL: Repository, https://github.com/hypergonial/hikari-arc
Project-URL: Issues, https://github.com/hypergonial/hikari-arc/issues
Project-URL: Changelog, https://arc.hypergonial.com/changelog/
Author-email: hypergonial <git@hypergonial.com>
Maintainer-email: hypergonial <git@hypergonial.com>
License-Expression: MIT
License-File: LICENSE
Classifier: Development Status :: 5 - Production/Stable
Classifier: Framework :: AsyncIO
Classifier: Intended Audience :: Developers
Classifier: Natural Language :: English
Classifier: Programming Language :: Python :: 3 :: Only
Classifier: Programming Language :: Python :: 3.10
Classifier: Programming Language :: Python :: 3.11
Classifier: Programming Language :: Python :: 3.12
Classifier: Programming Language :: Python :: 3.13
Classifier: Programming Language :: Python :: Implementation :: CPython
Classifier: Topic :: Software Development :: Libraries
Classifier: Topic :: Software Development :: Libraries :: Application Frameworks
Classifier: Topic :: Software Development :: Libraries :: Python Modules
Requires-Python: >=3.10
Requires-Dist: alluka<0.4,>=0.3.3
Requires-Dist: attrs>=25.3.0
Requires-Dist: hikari>=2.3.3
Provides-Extra: cron
Requires-Dist: croniter==5.0.1; extra == 'cron'
Requires-Dist: types-croniter==5.0.1.20241205; extra == 'cron'
Provides-Extra: rest
Requires-Dist: hikari[server]>=2.3.3; extra == 'rest'
